offline_translator/__init__.py
offline_translator/__main__.py
offline_translator/cli.py
offline_translator/core.py
offline_translator/info.py
offline_translator/py.typed
offline_translator/resources/logo.ico
offline_translator/resources/logo.png
offline_translator/ui.py
offline_translator-0.0.2.dist-info/LICENSE
offline_translator-0.0.2.dist-info/METADATA
offline_translator-0.0.2.dist-info/WHEEL
offline_translator-0.0.2.dist-info/entry_points.txt
offline_translator-0.0.2.dist-info/RECORD
