Metadata-Version: 2.1
Name: offline-translator
Version: 0.0.2
Summary: Offline Translator GUI using Opus-MT.
Home-page: https://github.com/Dashstrom/offline-translator
License: MIT
Keywords: python,translation,local,transformer,huggingface
Author: Dashstrom
Author-email: dashstrom.pro@gmail.com
Maintainer: Dashstrom
Maintainer-email: dashstrom.pro@gmail.com
Requires-Python: >=3.8
Classifier: Development Status :: 3 - Alpha
Classifier: Environment :: Console
Classifier: Framework :: Pytest
Classifier: Framework :: Sphinx
Classifier: Framework :: tox
Classifier: Intended Audience :: Developers
Classifier: Intended Audience :: System Administrators
Classifier: License :: OSI Approved :: MIT License
Classifier: Natural Language :: English
Classifier: Operating System :: OS Independent
Classifier: Programming Language :: Python :: 3
Classifier: Programming Language :: Python :: 3.8
Classifier: Programming Language :: Python :: 3.9
Classifier: Programming Language :: Python :: 3.10
Classifier: Programming Language :: Python :: 3.11
Classifier: Programming Language :: Python :: 3.12
Classifier: Programming Language :: Python :: 3 :: Only
Classifier: Typing :: Typed
Provides-Extra: cov
Provides-Extra: docs
Provides-Extra: format
Provides-Extra: lint
Provides-Extra: tasks
Provides-Extra: test
Requires-Dist: coverage[toml] (==7.4.1) ; extra == "cov"
Requires-Dist: mypy (==1.8.0) ; extra == "lint"
Requires-Dist: myst-parser (==2.0.0) ; extra == "docs"
Requires-Dist: numpy (>=1.24.4,<2.0.0)
Requires-Dist: poethepoet (==0.24.4) ; extra == "tasks"
Requires-Dist: pre-commit (==3.5.0) ; extra == "format"
Requires-Dist: pytest (==8.0.0) ; extra == "test" or extra == "cov" or extra == "lint"
Requires-Dist: pytest-cov (==4.1.0) ; extra == "cov"
Requires-Dist: pytest-mock (==3.12.0) ; extra == "test" or extra == "cov" or extra == "lint"
Requires-Dist: pywin32 (>=306,<307) ; sys_platform == "win32"
Requires-Dist: ruff (==0.2.0) ; extra == "lint"
Requires-Dist: sacremoses (>=0.1.1,<0.2.0)
Requires-Dist: sentencepiece (>=0.1.99,<0.2.0)
Requires-Dist: sphinx (==7.1.2) ; extra == "docs"
Requires-Dist: sphinx-rtd-theme (==2.0.0) ; extra == "docs"
Requires-Dist: sphinxcontrib-mermaid (==0.9.2) ; extra == "docs"
Requires-Dist: torch (>=2.2.0,<3.0.0)
Requires-Dist: transformers (>=4.37.2,<5.0.0)
Project-URL: Documentation, https://github.com/Dashstrom/offline-translator
Project-URL: Repository, https://github.com/Dashstrom/offline-translator
